{
  "type": "object",
  "properties": {
    "ContentControls": {
      "$ref": "ContentControlConfiguration.schema.json"
    },
    "DocumentManagement": {
      "$ref": "DocumentManagementConfiguration.schema.json"
    },
    "ConfigurationLocations": {
      "$ref": "ConfigurationLocationConfiguration.schema.json"
    },
    "ScriptConfiguration": {
      "$ref": "ScriptConfiguration.schema.json"
    },
    "AttachTemplateConfiguration": {
      "$ref": "AttachTemplateConfiguration.schema.json"
    },
    "Licence": {
      "$ref": "LicenceConfiguration.schema.json"
    },
    "Rules": {
      "$ref": "RulesConfiguration.schema.json"
    },
    "Debug": {
      "$ref": "DebugConfiguration.schema.json"
    }
  },
  "additionalProperties": false,
  "$schema": "http://json-schema.org/draft-07/schema#",
  "$id": "https://kutana-brochet.github.io/schemas/7.0/CoreConfiguration.schema.json",
  "title": "CoreConfiguration"
}